odoo/addons/l10n_br_coa/README.rst
odoo/addons/l10n_br_coa/__init__.py
odoo/addons/l10n_br_coa/__manifest__.py
odoo/addons/l10n_br_coa/data/account.account.tag.csv
odoo/addons/l10n_br_coa/data/l10n_br_coa_tax_accounts.csv
odoo/addons/l10n_br_coa/data/l10n_br_coa_tax_templates_accounts.csv
odoo/addons/l10n_br_coa/data/l10n_br_coa_template.xml
odoo/addons/l10n_br_coa/data/template/account.tax-br_oca.csv
odoo/addons/l10n_br_coa/data/template/account.tax.group-br_oca.csv
odoo/addons/l10n_br_coa/i18n/es.po
odoo/addons/l10n_br_coa/i18n/l10n_br_coa.pot
odoo/addons/l10n_br_coa/i18n/pt_BR.po
odoo/addons/l10n_br_coa/models/__init__.py
odoo/addons/l10n_br_coa/models/account_tax.py
odoo/addons/l10n_br_coa/models/account_tax_mixin.py
odoo/addons/l10n_br_coa/models/account_tax_template.py
odoo/addons/l10n_br_coa/models/template_br_oca.py
odoo/addons/l10n_br_coa/readme/CONFIGURE.md
odoo/addons/l10n_br_coa/readme/CONTRIBUTORS.md
odoo/addons/l10n_br_coa/readme/DESCRIPTION.md
odoo/addons/l10n_br_coa/readme/INSTALL.md
odoo/addons/l10n_br_coa/readme/ROADMAP.md
odoo/addons/l10n_br_coa/readme/USAGE.md
odoo/addons/l10n_br_coa/static/description/icon.png
odoo/addons/l10n_br_coa/static/description/index.html
odoo/addons/l10n_br_coa/tests/__init__.py
odoo/addons/l10n_br_coa/tests/test_coa_load.py
odoo/addons/l10n_br_coa/views/account_tax.xml
odoo/addons/l10n_br_coa/views/account_tax_template.xml
odoo_addon_l10n_br_coa-18.0.1.0.0.2.dist-info/METADATA
odoo_addon_l10n_br_coa-18.0.1.0.0.2.dist-info/WHEEL
odoo_addon_l10n_br_coa-18.0.1.0.0.2.dist-info/top_level.txt
odoo_addon_l10n_br_coa-18.0.1.0.0.2.dist-info/RECORD
